Workbook

Sheet Runs
A1: Quire Press: press runs and costs, first quarter 2026
A2: Job code | B2: Client | C2: Stock | D2: Quantity | E2: Unit cost | F2: Setup fee | G2: Total | H2: Delivered | I2: Margin
A3: QP-2601-01 | B3: Thornbury Tea Rooms | C3: Abbey Cream Wove | D3: 1200 | E3: 0.42 | F3: 85 | G3: =D3*E3+F3 -> 589 | H3: 46031 | I3: 0.34
A4: QP-2601-02 | B4: Sable & Ink Bindery | C4: Hollow Lane Cover | D4: 450 | E4: 0.96 | F4: 120 | G4: =D4*E4+F4 -> 552 | H4: 46035 | I4: 0.29
A5: QP-2601-03 | B5: The Printer's Devil Reading Room | C5: Fen Laid Text | D5: 2500 | E5: 0.31 | F5: 95 | G5: =D5*E5+F5 -> 870 | H5: 46037 | I5: 0.37
A6: QP-2601-04 | B6: Halyard Sail Loft | C6: Tallow Board | D6: 300 | E6: 1.45 | F6: 140 | G6: =D6*E6+F6 -> 575 | H6: 46041 | I6: 0.26
A7: QP-2601-05 | B7: Winterbourne Orchard | C7: Quire House Text | D7: 1800 | E7: 0.38 | F7: 75 | G7: =D7*E7+F7 -> 759 | H7: 46044 | I7: 0.33
A8: QP-2601-06 | B8: Copperline Coffee | C8: Ledger Bond | D8: 4000 | E8: 0.19 | F8: 60 | G8: =D8*E8+F8 -> 820 | H8: 46048 | I8: 0.41
A9: QP-2601-07 | B9: Melrose Chamber Choir | C9: Chapel Blue Laid | D9: 900 | E9: 0.44 | F9: 110 | G9: =D9*E9+F9 -> 506 | H9: 46051 | I9: 0.31
A10: QP-2602-01 | B10: Fennel Street Florists | C10: Riverbank Cotton Rag | D10: 240 | E10: 1.85 | F10: 165 | G10: =D10*E10+F10 -> 609 | H10: 46056 | I10: 0.24
A11: QP-2602-02 | B11: Ashgrove Veterinary | C11: Marsh Grey Wove | D11: 1500 | E11: 0.35 | F11: 70 | G11: =D11*E11+F11 -> 595 | H11: 46058 | I11: 0.35
A12: QP-2602-03 | B12: Bramble Hill Cidery | C12: Kiln Red Cover | D12: 600 | E12: 0.78 | F12: 130 | G12: =D12*E12+F12 -> 598 | H12: 46063 | I12: 0.28
A13: QP-2602-04 | B13: The Long Room Bookshop | C13: Abbey Cream Wove | D13: 2200 | E13: 0.33 | F13: 90 | G13: =D13*E13+F13 -> 816 | H13: 46065 | I13: 0.36
A14: QP-2602-05 | B14: Norwood Ceramics | C14: Nightwatch Black | D14: 350 | E14: 1.62 | F14: 155 | G14: =D14*E14+F14 -> 722 | H14: 46070 | I14: 0.22
... A24: QP-2603-07 | B24: Greylag Press Co-operative | C24: Marsh Grey Wove | D24: 1650 | E24: 0.36 | F24: 75 | G24: =D24*E24+F24 -> 669 | H24: 46105 | I24: 0.34
A25: QP-2603-08 | B25: Thornbury Tea Rooms | C25: Abbey Cream Wove | D25: 1400 | E25: 0.4 | F25: 85 | G25: =D25*E25+F25 -> 645 | I25: 0.35
A26: QP-2603-09 | B26: Little Ouse Sailing Trust | C26: Sedge Green Wove | D26: 950 | E26: 0.39 | F26: 95 | G26: =D26*E26+F26 -> 465.5 | H26: 46107 | I26: 0.31

Sheet Paper
A1: The paper rack: stocks held at the Mill Street shop, priced by the ream
A2: Stock name | B2: Weight (gsm) | C2: Colour | D2: Sheets per ream | E2: Price per ream | F2: Price per sheet
A3: Abbey Cream Wove | B3: 120 | C3: Cream | D3: 500 | E3: 62.5 | F3: =E3/D3 -> 0.125
A4: Fen Laid Text | B4: 90 | C4: Oatmeal | D4: 500 | E4: 47.5 | F4: =E4/D4 -> 0.095
A5: Hollow Lane Cover | B5: 250 | C5: Bone | D5: 250 | E5: 70 | F5: =E5/D5 -> 0.28
A6: Riverbank Cotton Rag | B6: 300 | C6: Natural white | D6: 100 | E6: 46 | F6: =E6/D6 -> 0.46
A7: Tallow Board | B7: 400 | C7: Slate | D7: 100 | E7: 58 | F7: =E7/D7 -> 0.58
A8: Marsh Grey Wove | B8: 110 | C8: Grey | D8: 500 | E8: 55 | F8: =E8/D8 -> 0.11
A9: Chapel Blue Laid | B9: 100 | C9: Pale blue | D9: 500 | E9: 60 | F9: =E9/D9 -> 0.12
A10: Ledger Bond | B10: 80 | C10: White | D10: 500 | E10: 37.5 | F10: =E10/D10 -> 0.075
A11: Quire House Text | B11: 135 | C11: Ivory | D11: 250 | E11: 41.25 | F11: =E11/D11 -> 0.165
A12: Kiln Red Cover | B12: 270 | C12: Terracotta | D12: 125 | E12: 43.75 | F12: =E12/D12 -> 0.35
A13: Sedge Green Wove | B13: 115 | C13: Sage | D13: 500 | E13: 57.5 | F13: =E13/D13 -> 0.115
A14: Nightwatch Black | B14: 300 | C14: Black | D14: 100 | E14: 52 | F14: =E14/D14 -> 0.52

Sheet Summary
A1: What the quarter came to, counted once and then counted again
A2: Measure | B2: Value | C2: Note from the pressroom
A3: Total invoiced | B3: =SUM(Runs!G3:G26) -> 15610.8 | C3: Every job on the Runs sheet, setup fees included.
A4: Jobs on the press | B4: =COUNTA(Runs!A3:A26) -> 24 | C4: Counted by job code, so a cancelled run would still show.
A5: Sheets through the press | B5: =SUM(Runs!D3:D26) -> 31650 | C5: Trimmed sheets, not make ready. Make ready never gets counted.
A6: Setup fees collected | B6: =SUM(Runs!F3:F26) -> 2525 | C6: The hours before the first good sheet, priced honestly.
A7: Average margin | B7: =AVERAGE(Runs!I3:I26) -> 0.31375 | C7: Steadier than last year, which is the whole point of the rate card.
A8: Largest single run | B8: =MAX(Runs!G3:G26) -> 905 | C8: Three thousand labels for the garden society, the biggest invoice of the quarter.
A9: Smallest single run | B9: =MIN(Runs!G3:G26) -> 454.6 | C9: A workshop's own stationery, priced kindly. Short runs keep the hand in.
A10: Average unit cost | B10: =AVERAGE(Runs!E3:E26) -> 0.7125 | C10: Per sheet, across every stock and every plate.
A11: Runs delivered | B11: =COUNT(Runs!H3:H26) -> 23 | C11: One job is still on the drying rack, so its date cell sits empty.
A12: Stocks in the rack | B12: =COUNTA(Paper!A3:A14) -> 12 | C12: Twelve is as many as the shop can shelve without warping a sheet.
A13: Cheapest sheet held | B13: =MIN(Paper!F3:F14) -> 0.075 | C13: Ledger bond, bought by the pallet, used for proofs and letters.
A14: Most used stock | B14: =INDEX(Paper!A3:A14,1) -> Abbey Cream Wove | C14: A cream wove that takes a deep impression and forgives a heavy hand.
A15: Runs on that stock | B15: =COUNTIF(Runs!C3:C26,Paper!A3) -> 3 | C15: Three jobs, two of them for the same tea rooms on Cobb Street.
A16: Quarter closed | B16: FALSE | C16: Not until the last delivery note comes back signed.
